versiontracker/__init__.py
versiontracker/_version.py
versiontracker/cli.py
versiontracker/data.yaml
versiontracker/items.py
versiontracker/pipelines.py
versiontracker/spiders/4k.py
versiontracker/spiders/__init__.py
versiontracker/spiders/apt.py
versiontracker/spiders/aqbanking.py
versiontracker/spiders/bitbucket.py
versiontracker/spiders/cgit.py
versiontracker/spiders/github.py
versiontracker/spiders/gitlab.py
versiontracker/spiders/gitweb.py
versiontracker/spiders/grass.py
versiontracker/spiders/hackage.py
versiontracker/spiders/http.py
versiontracker/spiders/kdegit.py
versiontracker/spiders/launchpad.py
versiontracker/spiders/nvidia.py
versiontracker/spiders/openbsd.py
versiontracker/spiders/opendesktop.py
versiontracker/spiders/pypi.py
versiontracker/spiders/sourceforge.py
versiontracker/spiders/text.py
versiontracker/spiders/thunderbird.py
versiontracker/spiders/xpath.py
versiontracker-2.1.4.20190921.data/scripts/versiontracker
versiontracker-2.1.4.20190921.dist-info/AUTHORS.rst
versiontracker-2.1.4.20190921.dist-info/LICENSE.rst
versiontracker-2.1.4.20190921.dist-info/METADATA
versiontracker-2.1.4.20190921.dist-info/WHEEL
versiontracker-2.1.4.20190921.dist-info/top_level.txt
versiontracker-2.1.4.20190921.dist-info/RECORD
