Metadata-Version: 2.1
Name: versiontracker
Version: 2.1.4.20190921
Summary: Web scrapping software to keep track of the latest stable version of different software.
Home-page: http://version-tracker.rtfd.io/
Author: Adrián Chaves (Gallaecio)
Author-email: adriyetichaves@gmail.com
License: AGPLv3+
Download-URL: https://gitlab.com/gallaecio/versiontracker/repository/archive.tar.gz?ref=v2.1.4.20190921
Platform: UNKNOWN
Classifier: Development Status :: 5 - Production/Stable
Classifier: Environment :: Console
Classifier: Intended Audience :: Developers
Classifier: License :: OSI Approved :: GNU Affero General Public License v3 or later (AGPLv3+)
Classifier: Operating System :: OS Independent
Classifier: Programming Language :: Python
Classifier: Programming Language :: Python :: 3
Classifier: Topic :: System :: Archiving :: Packaging
Requires-Dist: argcomplete
Requires-Dist: chardet
Requires-Dist: cryptography (<2)
Requires-Dist: dateparser
Requires-Dist: pyasn1
Requires-Dist: pyOpenSSL (<17.5.0)
Requires-Dist: pyxdg
Requires-Dist: PyYAML
Requires-Dist: Scrapy
Requires-Dist: sphinx-argparse
Requires-Dist: termcolor
